pystrictconfig/__init__.py
pystrictconfig/__main__.py
pystrictconfig/core.py
pystrictconfig/custom.py
pystrictconfig/schema.py
pystrictconfig/utils.py
pystrictconfig/yaml_loader.py
pystrictconfig-0.0.33.dist-info/LICENSE.txt
pystrictconfig-0.0.33.dist-info/METADATA
pystrictconfig-0.0.33.dist-info/WHEEL
pystrictconfig-0.0.33.dist-info/entry_points.txt
pystrictconfig-0.0.33.dist-info/top_level.txt
pystrictconfig-0.0.33.dist-info/RECORD
