Metadata-Version: 2.1
Name: pystrictconfig
Version: 0.0.33
Summary: A python package to enforce correctness of configuration values
Author-email: Ivan Lamperti <ivan.lamperti.work@gmail.com>
License: Copyright (c) 2016 The Python Packaging Authority (PyPA)
Project-URL: homepage, https://github.com/odococo/pystrictconfig
Project-URL: documentation, https://github.com/odococo/pystrictconfig
Project-URL: repository, https://github.com/odococo/pystrictconfig
Keywords: configuration
Classifier: Development Status :: 2 - Pre-Alpha
Requires-Python: >=3.9
License-File: LICENSE.txt
Requires-Dist: PyYAML (==6.0)
Requires-Dist: click
Provides-Extra: dev
Requires-Dist: tox ; extra == 'dev'
Requires-Dist: bumpver ; extra == 'dev'
Requires-Dist: pip-tools ; extra == 'dev'
Requires-Dist: twine ; extra == 'dev'
Provides-Extra: test
Requires-Dist: check-manifest ; extra == 'test'
Requires-Dist: pytest ; extra == 'test'
Requires-Dist: pytest-cov ; extra == 'test'
Requires-Dist: flake8 ; extra == 'test'
